pytorch_zoo/__init__.py
pytorch_zoo/data.py
pytorch_zoo/loss.py
pytorch_zoo/metrics.py
pytorch_zoo/modules.py
pytorch_zoo/schedulers.py
pytorch_zoo/utils.py
pytorch_zoo-1.2.2.dist-info/LICENSE
pytorch_zoo-1.2.2.dist-info/METADATA
pytorch_zoo-1.2.2.dist-info/WHEEL
pytorch_zoo-1.2.2.dist-info/top_level.txt
pytorch_zoo-1.2.2.dist-info/RECORD
