Metadata-Version: 2.1
Name: pytorch-zoo
Version: 1.2.2
Summary: A collection of useful modules and utilities for kaggle not available in Pytorch
Home-page: https://github.com/bkahn-github/pytorch_zoo
Author: Bilal Khan
Author-email: bk@tinymanager.com
License: UNKNOWN
Platform: UNKNOWN
Classifier: Programming Language :: Python :: 3
Classifier: License :: OSI Approved :: MIT License
Classifier: Operating System :: OS Independent
